machc/user/__init__.py
machc/user/entities/__init__.py
machc/user/entities/authenticated_person.py
machc/user/entities/login_credential.py
machc/user/entities/person.py
machc/user/entities/user.py
machc/user/entities/user_id.py
machc/user/entities/user_profile.py
machc/user/interactors/__init__.py
machc/user/interactors/login.py
machc/user/interactors/registration.py
machc/user/interactors/exception/__init__.py
machc/user/interactors/exception/user_exception.py
machc/user/interactors/stud/__init__.py
machc/user/interactors/stud/user_login_service.py
machc/user/interactors/stud/user_registration_service.py
machc_user-0.0.2.dist-info/METADATA
machc_user-0.0.2.dist-info/WHEEL
machc_user-0.0.2.dist-info/top_level.txt
machc_user-0.0.2.dist-info/RECORD
