Metadata-Version: 2.4
Name: machc.user
Version: 0.0.2
Summary: Provides essential entities and interactors for managing e-commerce user-related workflows, including authentication, user profiles, and business logic, while ensuring modularity and scalability within the Machc ecosystem.
Author-email: Viktor Tovstyi <viktor.tovstyi@gmail.com>
Requires-Python: ==3.12.3
Requires-Dist: machc.base==0.0.2
